{
  "crawled_at": "2020-12-19 01:44:30",
  "category": "보건복지",
  "begin": "2020-12-17",
  "end": "2021-01-16",
  "content": "안녕하세요. 현재 코로나19 때문에 모든 국민들이 힘든 시기를 살고 있습니다. 각 지역마다 동선을 조금이라도 알려주는데는 알려주고 알려주지 않는 곳은 알려주지 않는 곳이 있습니다. 현재 코로나19 확진자가 많이 나오는 상황에서 동선을 제대로 알려주지 않습니다. 현재 동작구청에서는 아예 알려주지도 않습니다. 아무리 개인정보보호법때문이라고 하지만 현재 상황이 상황인 만큼 어느정도 선에서는 알려주어야 하지 않을까 싶습니다. 정보공개 지침에서도 국민은 감염병 발생 상황, 감염병 예방 및 관리 등에 관한 정보와 대응방법을 알 권리가 있고, 국가와 지방자치단체는 신속하게 정보를 공개하여야 한다. 고 하는데 알려주는 건 아예 없습니다. 개인정보 보호 원칙 때문에 아예 알려주지 않고 있는 상황입니다. 현재 상황이 너무 않좋은쪽으로 가고 있는데 제대로 된 동선을 알려주시면 좋겠습니다.",
  "num_agree": 347,
  "petition_idx": "594760",
  "status": "청원진행중",
  "title": "코로나19 각 지역 동선좀 제대로 알려주세요"
}