{
  "crawled_at": "2020-12-19 01:45:15",
  "category": "경제민주화",
  "begin": "2020-12-18",
  "end": "2021-01-17",
  "content": "우리 현대엠엔소프트 소액주주들은 미래차 자율주행 패러다임 대전환의 시대를 맞아 현대차 그룹의 미래를 긍정적으로 보고, 특히, 본격적인 3세 경영시대를 맞이하여 그룹 내 모빌리티 전문회사인 현대엠엔소프트를 장기보유하며, 직상장을 기대하고 응원하던 주주들입니다.​ 그런데, 최근 불공정한 합병결정으로 소액주주들에게 크나큰 피해가 생겨 다음과 같은 청원을 상서합니다. ​ --------------------- 다 음 ---------------------- 먼저, 현대차그룹 정의선회장의 취임 후 첫 작품인 이번 합병에서 무리하게 소액주주의 집단반발을 사면서까지 국내 최고의 정밀지도 자율주행회사이자, 유니콘기업으로 기대받던 현대엠엔소프트를 헐값인 3천6백억대에 합병하는 것이 대기업 그룹으로써 해야만 하는 일인지, 재벌기업의 횡포가 아닌지 묻지 않을 수 없습니다. 합병은 그룹 차원의 전략적 의사결정이라고 백번양보하여 이해하더라도, 합병과정에서 재벌 그룹으로써 합병비율을 공정하게 유지할 사회적 책무가 있음을 상기시켜 드립니다. 한편, 합병비율 관련하여 1주당 가치와 시장가격에 대한 구체적인 자료를 보면 현대엠엔소프트와 현대오토에버의 1주당 자본총액은 각각 5만404원, 2만5836원이고, 현대엠엔소프트가 오토에버의 1.95배입니다. 또, 두 회사의 최근 3개월 시장가격(단순평균)을 산출해보면 각각 12만2608원, 7만8046원으로 현대엠엔소프트가 현대오토에버의 1.57배입니다. 그런데, 최근 합병공시에 따르면 현대엠엔소프트 주주들은 현대오토에버 주식을 최소 1.57주에서 약 2주를 받아야 마땅함에도, 오토에버의 0.95주 밖에 받지 못하게 되었습니다. 이것은 최근 그룹총수의 취임 시 강조한 '주주들의 권익' 도 함께하겠다는 모습이 결코 아닌 폭거입니다. 현 정부의 공정 가치를 흔드는 행위로 볼 수 있어 절대 묵과하여서는 아니됩니다. \" 과정은 공정하고, 결과는 정의로울 것\" 이라는 대통령님 말씀대로 우리 주주들은 금번 합병에서 공정한 합병 비율이 적용되기를 강력히 요구합니다.",
  "num_agree": 295,
  "petition_idx": "594793",
  "status": "청원진행중",
  "title": "현대엠엔소프트와 현대오토에버, 불공정한 합병비율 개선이 필요합니다"
}